{
	"identifier": "Level_0",
	"uniqueIdentifer": "504e0c60-6280-11ee-9b3a-bd257fff7a18",
	"x": 0,
	"y": 0,
	"width": 2000,
	"height": 256,
	"bgColor": "#232EDC",
	"neighbourLevels": [],
	"customFields": {
		"Goomba": "#E2E2E2",
		"Ground": "#3CA9EE",
		"GoombaTurnAround": "#DFA693",
		"Pipe": "#DC6E55",
		"Brick": "#ED553B"
	},
	"layers": [
		"Colors.png",
		"More_Colors.png"
	],
	"entities": {
		"PlayerStart": [
			{
				"id": "PlayerStart",
				"iid": "9bca20b0-6280-11ee-87e8-6b70c9794d3f",
				"layer": "Player_Entities",
				"x": 48,
				"y": 64,
				"width": 16,
				"height": 16,
				"color": 6539085,
				"customFields" : {}
			}
		]
	}
}